grafana_openai_monitoring/__handlers.py
grafana_openai_monitoring/__init__.py
grafana_openai_monitoring/chat_v1.py
grafana_openai_monitoring/chat_v2.py
grafana_openai_monitoring-0.0.9.dist-info/METADATA
grafana_openai_monitoring-0.0.9.dist-info/WHEEL
grafana_openai_monitoring-0.0.9.dist-info/RECORD
