Metadata-Version: 2.1
Name: grafana-openai-monitoring
Version: 0.0.9
Summary: Library to monitor your OpenAI usage and send metrics and logs to Grafana Cloud
Home-page: https://github.com/grafana/grafana-openai-monitoring
Keywords: observability,monitoring,openai,grafana,gpt
Author: Ishan Jain
Author-email: ishan.jain@grafana.com
Requires-Python: >=3.7.1,<4.0.0
Classifier: Programming Language :: Python :: 3
Classifier: Programming Language :: Python :: 3.8
Classifier: Programming Language :: Python :: 3.9
Classifier: Programming Language :: Python :: 3.10
Classifier: Programming Language :: Python :: 3.11
Classifier: Programming Language :: Python :: 3.12
Requires-Dist: requests (>=2.26.0,<3.0.0)
Project-URL: Repository, https://github.com/grafana/grafana-openai-monitoring
